TkSel/TkSel.py
TkSel/__about__.py
TkSel/__init__.py
TkSel/main.py
TkSel/pedro.mp3
tksel-1.1.3.dist-info/METADATA
tksel-1.1.3.dist-info/WHEEL
tksel-1.1.3.dist-info/entry_points.txt
tksel-1.1.3.dist-info/licenses/LICENSE.txt
tksel-1.1.3.dist-info/RECORD
