Metadata-Version: 2.3
Name: tksel
Version: 1.1.3
Summary: Scrapper for Minet csvs on tiktok
Project-URL: Documentation, https://github.com/Marceau-h/TkSel#readme
Project-URL: Issues, https://github.com/Marceau-h/TkSel/issues
Project-URL: Source, https://github.com/Marceau-h/TkSel
Author-email: Marceau-h <pypi@marceau-h.fr>
Maintainer-email: Marceau-h <pypi@marceau-h.fr>
License-Expression: AGPL-3.0-or-later
License-File: LICENSE.txt
Keywords: TikTok,minet,tksel,video
Classifier: Development Status :: 4 - Beta
Classifier: License :: OSI Approved :: GNU Affero General Public License v3 or later (AGPLv3+)
Classifier: Operating System :: OS Independent
Classifier: Programming Language :: Python
Classifier: Programming Language :: Python :: 3.7
Classifier: Programming Language :: Python :: 3.8
Classifier: Programming Language :: Python :: 3.9
Classifier: Programming Language :: Python :: 3.10
Classifier: Programming Language :: Python :: 3.11
Classifier: Programming Language :: Python :: Implementation :: CPython
Classifier: Programming Language :: Python :: Implementation :: PyPy
Requires-Python: >=3.7
Requires-Dist: chromedriver-autoinstaller-fix
Requires-Dist: polars
Requires-Dist: python-vlc
Requires-Dist: requests
Requires-Dist: selenium
Requires-Dist: tqdm
